README
setup.py
django_guardianpie.egg-info/PKG-INFO
django_guardianpie.egg-info/SOURCES.txt
django_guardianpie.egg-info/dependency_links.txt
django_guardianpie.egg-info/requires.txt
django_guardianpie.egg-info/top_level.txt
guardianpie/__init__.py
guardianpie/authorization.py
guardianpie/resources.py