Metadata-Version: 1.0
Name: django-guardianpie
Version: 0.0.3
Summary: Tastypie authorization class that handles guardian permissions.
Home-page: http://github.com/airtonix/django-guardianpie
Author: Zenobius Jiricek
Author-email: airtonix@gmail.com
License: UNKNOWN
Platform: UNKNOWN
